{
  "topic": "mcqs",
  "content": "{\n  \"questions\": [\n    {\n      \"question\": \"What is the primary characteristic of a completely randomized design?\",\n      \"options\": [\"A) All treatments are randomly assigned to each block\", \"B) Each treatment is applied to every block\", \"C) Each block contains only one treatment\", \"D) Each treatment is applied to every block\"],\n      \"correct\": 0,\n      \"explanation\": \"In a completely randomized design, every treatment is applied to every block, allowing for a fair comparison between treatments"
}
