{
  "type": "flowchart",
  "title": "C++ Inheritance Hierarchy Diagram",
  "description": "Visual representation of inheritance relationships between base and derived classes, highlighting protected member accessibility",
  "elements": [
    "Base Class (Parent)",
    "Derived Class 1 (Child)",
    "Derived Class 2 (Child)",
    "Protected Members",
    "Public Members",
    "Private Members"
  ],
  "relationships": [
    "Inheritance arrows from derived classes to base class",
    "Protected members accessible within derived classes",
    "Public interface exposed to external code",
    "Private members hidden from derived classes"
  ]
}
