{
  "questions": [
    {
      "question": "For each function f(x) = 2x + 1 and g(x) = x + 3, find the composition (g \u2218 f)(x) and simplify.",
      "type": "short_answer",
      "marks": 10,
      "hint": "None"
    },
    {
      "question": "If f(x) is the inverse of g(x) = 3x^2 + 2, what is f(-1)?",
      "type": "short_answer",
      "marks": 10,
      "hint": "None"
    },
    {
      "question": "Let f(x) = 1/x and g(x) = \u221ax. Find the inverse of the function (f \u2218 g)(x) and explain its properties.",
      "type": "long_answer",
      "marks": 25,
      "hint": "None"
    }
  ]
}
