{
  "diagrams": [
    {
      "id": "d-1",
      "title": "Prolog Program Structure",
      "description": "Shows the three main components of a Prolog program and their relationships",
      "elements": [
        "Knowledge Base (Facts + Rules)",
        "Query/Goal",
        "Unification & Backtracking Engine"
      ],
      "purpose": "Understanding how Prolog programs are organized and executed"
    },
    {
      "id": "d-2",
      "title": "Backtracking Search Tree",
      "description": "Visual representation of how Prolog explores solution paths with backtracking",
      "elements": [
        "Goal Node",
        "Choice Points (branches)",
        "Success Path (green)",
        "Failure Path (red)",
        "Backtrack Point (return to previous choice)"
      ],
      "purpose": "Visualizing how Prolog finds multiple solutions through backtracking"
    },
    {
      "id": "d-3",
      "title": "List Structure in Prolog",
      "description": "Shows how lists are represented with head-tail decomposition",
      "elements": [
        "List: [a,b,c,d]",
        "Head: a",
        "Tail: [b,c,d]",
        "Recursive decomposition",
        "Empty list: []"
      ],
      "purpose": "Understanding list processing in Prolog through head-tail notation"
    }
  ],
  "topicId": "introduction-to-prolog",
  "svgFile": "assets/diagram.svg"
}