{
  "topicId": "platforms-for-decentralization",
  "questions": [
    {
      "id": "q1",
      "type": "short",
      "question": "What is decentralization in blockchain technology?",
      "marks": 5,
      "keyPoints": [
        "Definition of decentralization",
        "Importance of decentralization in blockchain technology"
      ]
    },
    {
      "id": "q2",
      "type": "short",
      "question": "What are the different types of decentralization platforms?",
      "marks": 5,
      "keyPoints": ["Blockchain-based platforms", "Non-blockchain-based platforms"]
    },
    {
      "id": "q3",
      "type": "long",
      "question": "What are the characteristics of decentralization platforms?",
      "marks": 10,
      "keyPoints": ["Decentralized network", "Open-source", "Autonomy", "Security"]
    },
    {
      "id": "q4",
      "type": "long",
      "question": "What are the use cases for decentralization platforms?",
      "marks": 10,
      "keyPoints": ["DeFi", "Social media", "Gaming"]
    },
    {
      "id": "q5",
      "type": "short",
      "question": "What is Polkadot?",
      "marks": 5,
      "keyPoints": ["Definition of Polkadot", "Importance of Polkadot in blockchain technology"]
    },
    {
      "id": "q6",
      "type": "short",
      "question": "What is Solana?",
      "marks": 5,
      "keyPoints": ["Definition of Solana", "Importance of Solana in blockchain technology"]
    },
    {
      "id": "q7",
      "type": "long",
      "question": "Compare and contrast blockchain-based and non-blockchain-based decentralization platforms.",
      "marks": 10,
      "keyPoints": [
        "Similarities and differences between blockchain-based and non-blockchain-based platforms"
      ]
    }
  ]
}
