{
  "topicId": "introduction-need-for-machine-learning",
  "flashcards": [
    {
      "id": "fc1",
      "front": "What is Machine Learning?",
      "back": "A field of study that gives computers the ability to learn from data without being explicitly programmed."
    },
    {
      "id": "fc2",
      "front": "Name the three main types of Machine Learning.",
      "back": "Supervised Learning, Unsupervised Learning, and Reinforcement Learning."
    },
    {
      "id": "fc3",
      "front": "What is the difference between classification and regression?",
      "back": "Classification predicts categorical labels, while regression predicts continuous values."
    },
    {
      "id": "fc4",
      "front": "What is overfitting in Machine Learning?",
      "back": "When a model learns the training data too well, including noise, and performs poorly on new data."
    },
    {
      "id": "fc5",
      "front": "What is feature engineering?",
      "back": "The process of creating new input features or transforming existing features to improve model performance."
    }
  ]
}