{
  "topicId": "transfer-learning",
  "questions": [
    {
      "id": "q-1",
      "type": "short",
      "question": "Explain two scenarios where transfer learning is ineffective",
      "keyPoints": [
        "When source/target domains are unrelated",
        "When target dataset is sufficiently large"
      ],
      "marks": 5
    },
    {
      "id": "q-2",
      "type": "long",
      "question": "Compare feature extraction vs fine-tuning approaches",
      "keyPoints": [
        "Feature extraction keeps base model frozen",
        "Fine-tuning allows partial weight updates",
        "Computational requirements differ",
        "Data size considerations"
      ],
      "marks": 10
    }
  ]
}