{
  "topicId": "transformation-in-homogeneous-coordinates",
  "mcqs": [
    {
      "id": "mcq-1",
      "question": "In homogeneous coordinates, a 2D point (x, y) is represented as:",
      "options": [
        {
          "key": "A",
          "text": "(x, y, 0)"
        },
        {
          "key": "B",
          "text": "(x, y, 1)"
        },
        {
          "key": "C",
          "text": "(x, y, w)"
        },
        {
          "key": "D",
          "text": "(x, y, 2)"
        }
      ],
      "correctAnswer": "(x, y, 1)",
      "explanation": "For standard representation, we use w=1 so (x, y) becomes (x, y, 1) in homogeneous coordinates.",
      "difficulty": "easy"
    },
    {
      "id": "mcq-2",
      "question": "Which transformation cannot be represented as a linear transformation in 2D Cartesian coordinates but can be in homogeneous coordinates?",
      "options": [
        {
          "key": "A",
          "text": "Rotation"
        },
        {
          "key": "B",
          "text": "Scaling"
        },
        {
          "key": "C",
          "text": "Translation"
        },
        {
          "key": "D",
          "text": "Shearing"
        }
      ],
      "correctAnswer": "Translation",
      "explanation": "Translation adds constants to coordinates, which is not linear. Homogeneous coordinates make it a matrix multiplication.",
      "difficulty": "easy"
    },
    {
      "id": "mcq-3",
      "question": "The homogeneous translation matrix for translating by (5, 3) is:",
      "options": [
        {
          "key": "A",
          "text": "[1 0 5; 0 1 3; 0 0 1]"
        },
        {
          "key": "B",
          "text": "[5 0 1; 0 3 1; 0 0 1]"
        },
        {
          "key": "C",
          "text": "[1 5 0; 0 1 3; 0 0 1]"
        },
        {
          "key": "D",
          "text": "[5 3 1; 0 0 1; 0 0 1]"
        }
      ],
      "correctAnswer": "[1 0 5; 0 1 3; 0 0 1]",
      "explanation": "Translation matrix has identity in top-left 2×2, translation values in third column.",
      "difficulty": "easy"
    },
    {
      "id": "mcq-4",
      "question": "A point (3, 4) translated by (2, -1) in homogeneous coordinates results in:",
      "options": [
        {
          "key": "A",
          "text": "(5, 3)"
        },
        {
          "key": "B",
          "text": "(5, 3, 1)"
        },
        {
          "key": "C",
          "text": "(3, 4, 0)"
        },
        {
          "key": "D",
          "text": "(6, -4)"
        }
      ],
      "correctAnswer": "(5, 3, 1)",
      "explanation": "Adding translation: x' = 3+2 = 5, y' = 4+(-1) = 3, maintaining w=1 gives (5,3,1).",
      "difficulty": "medium"
    },
    {
      "id": "mcq-5",
      "question": "The rotation matrix for 90° counterclockwise about origin is:",
      "options": [
        {
          "key": "A",
          "text": "[0 -1 0; 1 0 0; 0 0 1]"
        },
        {
          "key": "B",
          "text": "[1 0 0; 0 1 0; 0 0 1]"
        },
        {
          "key": "C",
          "text": "[0 1 0; -1 0 0; 0 0 1]"
        },
        {
          "key": "D",
          "text": "[-1 0 0; 0 -1 0; 0 0 1]"
        }
      ],
      "correctAnswer": "[0 -1 0; 1 0 0; 0 0 1]",
      "explanation": "At 90°, cos=0, sin=1, giving [0 -1; 1 0] in the rotation submatrix.",
      "difficulty": "medium"
    },
    {
      "id": "mcq-6",
      "question": "Scaling by factor 2 in both x and y direction is represented by:",
      "options": [
        {
          "key": "A",
          "text": "[2 0 0; 0 2 0; 0 0 1]"
        },
        {
          "key": "B",
          "text": "[1 0 2; 0 1 2; 0 0 1]"
        },
        {
          "key": "C",
          "text": "[2 0 1; 0 2 1; 0 0 1]"
        },
        {
          "key": "D",
          "text": "[1 1 0; 0 1 0; 0 0 1]"
        }
      ],
      "correctAnswer": "[2 0 0; 0 2 0; 0 0 1]",
      "explanation": "Scaling matrix places scale factors in diagonal positions: [sx 0 0; 0 sy 0; 0 0 1].",
      "difficulty": "easy"
    },
    {
      "id": "mcq-7",
      "question": "In homogeneous coordinates, the purpose of w component is to:",
      "options": [
        {
          "key": "A",
          "text": "Represent depth only"
        },
        {
          "key": "B",
          "text": "Enable matrix multiplication for all transformations"
        },
        {
          "key": "C",
          "text": "Represent color"
        },
        {
          "key": "D",
          "text": "Store object ID"
        }
      ],
      "correctAnswer": "Enable matrix multiplication for all transformations",
      "explanation": "The w coordinate allows translation to be expressed as matrix multiplication, unifying all transformations.",
      "difficulty": "medium"
    },
    {
      "id": "mcq-8",
      "question": "What does a vector (vx, vy, 0) represent in homogeneous coordinates?",
      "options": [
        {
          "key": "A",
          "text": "A point at origin"
        },
        {
          "key": "B",
          "text": "A direction/vector"
        },
        {
          "key": "C",
          "text": "A point at infinity"
        },
        {
          "key": "D",
          "text": "An error condition"
        }
      ],
      "correctAnswer": "A direction/vector",
      "explanation": "Vectors have w=0 because translation should not affect direction; only position points have w=1.",
      "difficulty": "medium"
    },
    {
      "id": "mcq-9",
      "question": "To rotate a point about a pivot (px, py), the correct order of composite transformation is:",
      "options": [
        {
          "key": "A",
          "text": "Translate → Rotate → Translate back"
        },
        {
          "key": "B",
          "text": "Rotate → Translate"
        },
        {
          "key": "C",
          "text": "Translate → Rotate"
        },
        {
          "key": "D",
          "text": "Rotate → Translate → Rotate"
        }
      ],
      "correctAnswer": "Translate → Rotate → Translate back",
      "explanation": "First translate so pivot is at origin, rotate, then translate back to original position.",
      "difficulty": "hard"
    },
    {
      "id": "mcq-10",
      "question": "The homogeneous matrix for reflection about x-axis is:",
      "options": [
        {
          "key": "A",
          "text": "[1 0 0; 0 -1 0; 0 0 1]"
        },
        {
          "key": "B",
          "text": "[-1 0 0; 0 1 0; 0 0 1]"
        },
        {
          "key": "C",
          "text": "[0 1 0; 1 0 0; 0 0 1]"
        },
        {
          "key": "D",
          "text": "[1 0 0; 0 1 0; 0 0 -1]"
        }
      ],
      "correctAnswer": "[1 0 0; 0 -1 0; 0 0 1]",
      "explanation": "Reflection negates one coordinate. About x-axis, y becomes -y, represented by [1 0; 0 -1].",
      "difficulty": "medium"
    },
    {
      "id": "mcq-11",
      "question": "For a point (6, 8, 2) in homogeneous coordinates, the Cartesian equivalent is:",
      "options": [
        {
          "key": "A",
          "text": "(3, 4)"
        },
        {
          "key": "B",
          "text": "(8, 10)"
        },
        {
          "key": "C",
          "text": "(6, 8)"
        },
        {
          "key": "D",
          "text": "(3, 4, 1)"
        }
      ],
      "correctAnswer": "(3, 4)",
      "explanation": "Convert by dividing by w: (6/2, 8/2) = (3, 4). The w=2 indicates a perspective transformation.",
      "difficulty": "medium"
    },
    {
      "id": "mcq-12",
      "question": "The shearing transformation matrix in x-direction with factor 0.5 is:",
      "options": [
        {
          "key": "A",
          "text": "[1 0.5 0; 0 1 0; 0 0 1]"
        },
        {
          "key": "B",
          "text": "[1 0 0; 0.5 1 0; 0 0 1]"
        },
        {
          "key": "C",
          "text": "[0.5 1 0; 1 0.5 0; 0 0 1]"
        },
        {
          "key": "D",
          "text": "[1 0 0.5; 0 1 0; 0 0 1]"
        }
      ],
      "correctAnswer": "[1 0.5 0; 0 1 0; 0 0 1]",
      "explanation": "X-shear keeps y same, x changes by shx × y, represented in matrix as [1 shx 0; 0 1 0; 0 0 1].",
      "difficulty": "hard"
    },
    {
      "id": "mcq-13",
      "question": "What is the 3D homogeneous transformation matrix size?",
      "options": [
        {
          "key": "A",
          "text": "2×2"
        },
        {
          "key": "B",
          "text": "3×3"
        },
        {
          "key": "C",
          "text": "4×4"
        },
        {
          "key": "D",
          "text": "5×5"
        }
      ],
      "correctAnswer": "4×4",
      "explanation": "3D points (x, y, z) become (x, y, z, w) in homogeneous coordinates, requiring a 4×4 matrix.",
      "difficulty": "easy"
    },
    {
      "id": "mcq-14",
      "question": "Matrix multiplication for transformations is:",
      "options": [
        {
          "key": "A",
          "text": "Commutative"
        },
        {
          "key": "B",
          "text": "Associative"
        },
        {
          "key": "C",
          "text": "Distributive over addition"
        },
        {
          "key": "D",
          "text": "All of the above"
        }
      ],
      "correctAnswer": "Associative",
      "explanation": "Matrix multiplication is associative: A×(B×C) = (A×B)×C, but not commutative: A×B ≠ B×A generally.",
      "difficulty": "hard"
    },
    {
      "id": "mcq-15",
      "question": "The identity matrix in 3×3 homogeneous form is:",
      "options": [
        {
          "key": "A",
          "text": "[1 1 1; 1 1 1; 1 1 1]"
        },
        {
          "key": "B",
          "text": "[1 0 0; 0 1 0; 0 0 1]"
        },
        {
          "key": "C",
          "text": "[0 1 0; 1 0 0; 0 0 1]"
        },
        {
          "key": "D",
          "text": "[1 0 1; 0 1 0; 1 0 1]"
        }
      ],
      "correctAnswer": "[1 0 0; 0 1 0; 0 0 1]",
      "explanation": "Identity matrix has 1s on diagonal, 0s elsewhere. It leaves points unchanged when multiplied.",
      "difficulty": "easy"
    },
    {
      "id": "mcq-16",
      "question": "To scale about a fixed point (px, py), the composite transformation is:",
      "options": [
        {
          "key": "A",
          "text": "Translate(-px,-py) → Scale → Translate(px,py)"
        },
        {
          "key": "B",
          "text": "Scale → Translate"
        },
        {
          "key": "C",
          "text": "Translate → Scale → Translate"
        },
        {
          "key": "D",
          "text": "Scale → Translate(-px,-py)"
        }
      ],
      "correctAnswer": "Translate(-px,-py) → Scale → Translate(px,py)",
      "explanation": "First move pivot to origin, scale, then move back to original position.",
      "difficulty": "hard"
    },
    {
      "id": "mcq-17",
      "question": "Homogeneous coordinates allow representation of points at infinity using:",
      "options": [
        {
          "key": "A",
          "text": "w = 0"
        },
        {
          "key": "B",
          "text": "w = 1"
        },
        {
          "key": "C",
          "text": "w = ∞"
        },
        {
          "key": "D",
          "text": "w = -1"
        }
      ],
      "correctAnswer": "w = 0",
      "explanation": "Points with w=0 in homogeneous coordinates represent directions/points at infinity, used in perspective projection.",
      "difficulty": "medium"
    },
    {
      "id": "mcq-18",
      "question": "A counterclockwise rotation by θ followed by translation by (tx, ty) requires matrix:",
      "options": [
        {
          "key": "A",
          "text": "T × R"
        },
        {
          "key": "B",
          "text": "R × T"
        },
        {
          "key": "C",
          "text": "T + R"
        },
        {
          "key": "D",
          "text": "R + T"
        }
      ],
      "correctAnswer": "T × R",
      "explanation": "Transformations apply right to left. Point is first rotated (R), then translated (T), so composite is T×R.",
      "difficulty": "hard"
    },
    {
      "id": "mcq-19",
      "question": "The homogeneous rotation matrix for 180° about z-axis in 3D is:",
      "options": [
        {
          "key": "A",
          "text": "[-1 0 0 0; 0 -1 0 0; 0 0 1 0; 0 0 0 1]"
        },
        {
          "key": "B",
          "text": "[1 0 0 0; 0 1 0 0; 0 0 -1 0; 0 0 0 1]"
        },
        {
          "key": "C",
          "text": "[0 -1 0 0; 1 0 0 0; 0 0 1 0; 0 0 0 1]"
        },
        {
          "key": "D",
          "text": "[-1 0 0 0; 0 -1 0 0; 0 0 -1 0; 0 0 0 1]"
        }
      ],
      "correctAnswer": "[-1 0 0 0; 0 -1 0 0; 0 0 1 0; 0 0 0 1]",
      "explanation": "At 180°, cos=-1, sin=0, giving rotation in xy-plane as [cos -sin; sin cos] = [-1 0; 0 -1].",
      "difficulty": "hard"
    },
    {
      "id": "mcq-20",
      "question": "Which is NOT a property of transformation matrices in homogeneous coordinates?",
      "options": [
        {
          "key": "A",
          "text": "Can represent all affine transformations"
        },
        {
          "key": "B",
          "text": "Matrix multiplication is commutative"
        },
        {
          "key": "C",
          "text": "Enables perspective transformations"
        },
        {
          "key": "D",
          "text": "Unified representation"
        }
      ],
      "correctAnswer": "Matrix multiplication is commutative",
      "explanation": "Matrix multiplication is not commutative in general, which is why transformation order matters in composite transforms.",
      "difficulty": "medium"
    }
  ]
}
