{
  "mnemonics": [
    {
      "id": "m-1",
      "title": "Visualization Tools",
      "content": "TAG DPQ-KG: Tableau, Apache Superset, Grafana, D3.js, Power BI, QlikView, Kepler.gl"
    }
  ],
  "acronyms": [
    {
      "term": "VQL",
      "expansion": "Visual Query Language",
      "usage": "Used in tools like Plotly for declarative visualization specs"
    }
  ],
  "visualTips": [
    {
      "concept": "Stream Processing",
      "visualization": "Imagine waterfall flowing into dashboard with live counters"
    }
  ],
  "analogies": [
    {
      "concept": "Distributed Rendering",
      "analogy": "Like a mural painting team where each artist works on different wall sections simultaneously"
    }
  ],
  "topicId": "visualization-tools"
}