{
  "chapterId": "module-2",
  "chapterTitle": "Module 2",
  "hasTopics": true,
  "topics": [
    {
      "id": "multithreading-models",
      "title": "Multithreading Models",
      "order": 6,
      "estimatedMinutes": 15,
      "hasVisual": true,
      "hasQuestions": true
    },
    {
      "id": "operations-on-processes",
      "title": "Operations On Processes",
      "order": 4,
      "estimatedMinutes": 15,
      "hasVisual": true,
      "hasQuestions": true
    },
    {
      "id": "overview",
      "title": "Overview",
      "order": 5,
      "estimatedMinutes": 15,
      "hasVisual": true,
      "hasQuestions": true
    },
    {
      "id": "process-concept",
      "title": "Process Concept",
      "order": 2,
      "estimatedMinutes": 15,
      "hasVisual": true,
      "hasQuestions": true
    },
    {
      "id": "process-management",
      "title": "Process Management",
      "order": 1,
      "estimatedMinutes": 15,
      "hasVisual": true,
      "hasQuestions": true
    },
    {
      "id": "process-scheduling",
      "title": "Process Scheduling",
      "order": 3,
      "estimatedMinutes": 15,
      "hasVisual": true,
      "hasQuestions": true
    },
    {
      "id": "thread-libraries",
      "title": "Thread Libraries",
      "order": 7,
      "estimatedMinutes": 15,
      "hasVisual": true,
      "hasQuestions": true
    }
  ]
}
