{
  "topicId": "opening-and-closing",
  "visuals": [
    {
      "id": "opening-closing-svg",
      "title": "Flow of Morphological Operations",
      "description": "Visual diagram for Flow of Morphological Operations",
      "type": "animated-svg",
      "file": "assets/opening-and-closing.svg",
      "animated": true
    }
  ],
  "diagrams": [
    {
      "id": "d1",
      "title": "Flow of Morphological Operations",
      "type": "flow",
      "content": {
        "nodes": [
          {
            "id": "n1",
            "label": "Original Image A"
          },
          {
            "id": "n2",
            "label": "Erosion (A ⊖ B)"
          },
          {
            "id": "n3",
            "label": "Dilation ( (A ⊖ B) ⊕ B )",
            "style": "fill:#e1f5fe"
          },
          {
            "id": "n4",
            "label": "Dilation (A ⊕ B)"
          },
          {
            "id": "n5",
            "label": "Erosion ( (A ⊕ B) ⊖ B )",
            "style": "fill:#f1f8e9"
          }
        ],
        "edges": [
          {
            "from": "n1",
            "to": "n2",
            "label": "For Opening"
          },
          {
            "from": "n2",
            "to": "n3",
            "label": "Then"
          },
          {
            "from": "n1",
            "to": "n4",
            "label": "For Closing"
          },
          {
            "from": "n4",
            "to": "n5",
            "label": "Then"
          }
        ]
      }
    },
    {
      "id": "d2",
      "title": "Effect of Opening and Closing",
      "type": "flow",
      "content": {
        "nodes": [
          {
            "id": "n1",
            "label": "Input Image"
          },
          {
            "id": "n2",
            "label": "Has small protrusions?",
            "shape": "diamond"
          },
          {
            "id": "n3",
            "label": "Apply Opening (∘)"
          },
          {
            "id": "n4",
            "label": "Result: Protrusions removed"
          },
          {
            "id": "n5",
            "label": "Has small holes?",
            "shape": "diamond"
          },
          {
            "id": "n6",
            "label": "Apply Closing (•)"
          },
          {
            "id": "n7",
            "label": "Result: Holes filled"
          }
        ],
        "edges": [
          {
            "from": "n1",
            "to": "n2"
          },
          {
            "from": "n2",
            "to": "n3",
            "label": "Yes"
          },
          {
            "from": "n3",
            "to": "n4"
          },
          {
            "from": "n2",
            "to": "n5",
            "label": "No"
          },
          {
            "from": "n5",
            "to": "n6",
            "label": "Yes"
          },
          {
            "from": "n6",
            "to": "n7"
          },
          {
            "from": "n5",
            "to": "n1",
            "label": "No",
            "style": "dashed"
          }
        ]
      }
    }
  ]
}
