[
  {
    "id": "sa1",
    "question": "State and briefly explain the Commutative Law, Associative Law, and Distributive Law as they apply to Boolean algebra.",
    "expectedPoints": [
      "Commutative Law: The order of variables does not affect the result of an AND or OR operation (e.g., A+B = B+A, AB = BA).",
      "Associative Law: The grouping of variables does not affect the result of an AND or OR operation (e.g., A+(B+C) = (A+B)+C, A(BC) = (AB)C).",
      "Distributive Law: AND distributes over OR and OR distributes over AND (e.g., A(B+C) = AB+AC, A+BC = (A+B)(A+C))."
    ],
    "marks": 2
  },
  {
    "id": "sa2",
    "question": "Using the basic theorems of Boolean algebra, simplify the expression F = A'B'C + A'BC + ABC' + ABC. Show each step and state the theorem used.",
    "expectedPoints": [
      "Factor out common terms: F = A'C(B' + B) + AB(C' + C).",
      "Apply the Complement Theorem: (B' + B) = 1 and (C' + C) = 1.",
      "Simplify using the Identity Theorem: F = A'C(1) + AB(1) = A'C + AB."
    ],
    "marks": 5
  },
  {
    "id": "sa3",
    "question": "Prove the validity of the Absorption Theorem (X + XY = X) using only the fundamental axioms and properties of Boolean algebra (Identity, Null, Idempotency, Complement, Involution). Do not use truth tables.",
    "expectedPoints": [
      "Start with the expression X + XY and apply the Distributive Law in reverse: X + XY = X(1 + Y).",
      "Apply the Null Theorem to (1 + Y): 1 + Y = 1, as ORing any variable with 1 yields 1.",
      "Apply the Identity Theorem: X(1) = X. Therefore, X + XY = X, proving the theorem."
    ],
    "marks": 10
  }
]