{
  "topicId": "module-4-exit",
  "diagrams": [
    {
      "id": "d-1",
      "title": "Exit Status Code Spectrum",
      "description": "Visual representation of exit status values and their meanings",
      "elements": [
        "0 (Success - Green zone)",
        "1 (General Error)",
        "2 (Misuse/Invalid arguments)",
        "126 (Not executable)",
        "127 (Command not found)",
        "128+N (Signal N termination)",
        "1-255 range shown as increasing error severity"
      ],
      "purpose": "Understanding exit code classification and when each is used"
    },
    {
      "id": "d-2",
      "title": "$? Variable Lifecycle",
      "description": "Timeline showing how $? gets overwritten",
      "elements": [
        "Command A executes (sets $?=0)",
        "Check $? immediately",
        "Command B executes (sets $?=1)",
        "Previous $?=0 is LOST",
        "Check $? immediately after each command"
      ],
      "purpose": "Emphasizing immediate checking of exit status"
    },
    {
      "id": "d-3",
      "title": "Signal to Exit Code Mapping",
      "description": "Formula: Exit Code = 128 + Signal Number",
      "elements": [
        "Signal 1 (SIGHUP) → Exit 129",
        "Signal 2 (SIGINT/Ctrl+C) → Exit 130",
        "Signal 9 (SIGKILL) → Exit 137",
        "Signal 15 (SIGTERM) → Exit 143",
        "Base value 128 shown as foundation"
      ],
      "purpose": "Understanding how signals translate to exit codes"
    },
    {
      "id": "d-4",
      "title": "Pipeline Exit Status Behavior",
      "description": "Comparison of default vs pipefail behavior",
      "elements": [
        "Command1 | Command2 | Command3",
        "Default: returns status of Command3 only",
        "With pipefail: returns status of rightmost failed command",
        "All succeed: returns 0 in both cases"
      ],
      "purpose": "Understanding how to properly handle errors in pipelines"
    }
  ],
  "visuals": [
    {
      "id": "exit-svg",
      "title": "Exit",
      "description": "Visual diagram for exit",
      "type": "animated-svg",
      "file": "assets/exit.svg",
      "svgContent": "<placeholder>",
      "animated": true
    }
  ]
}
